letsencrypt_apache/__init__.py
letsencrypt_apache-0.7.0.dist-info/DESCRIPTION.rst
letsencrypt_apache-0.7.0.dist-info/METADATA
letsencrypt_apache-0.7.0.dist-info/RECORD
letsencrypt_apache-0.7.0.dist-info/WHEEL
letsencrypt_apache-0.7.0.dist-info/metadata.json
letsencrypt_apache-0.7.0.dist-info/top_level.txt
