Metadata-Version: 2.0
Name: letsencrypt-apache
Version: 0.7.0
Summary: Apache plugin for Let's Encrypt
Home-page: https://github.com/letsencrypt/letsencrypt
Author: Certbot Project
Author-email: client-dev@letsencrypt.org
License: Apache License 2.0
Platform: UNKNOWN
Classifier: Development Status :: 3 - Alpha
Classifier: Environment :: Plugins
Classifier: Intended Audience :: System Administrators
Classifier: License :: OSI Approved :: Apache Software License
Classifier: Operating System :: POSIX :: Linux
Classifier: Programming Language :: Python
Classifier: Programming Language :: Python :: 2
Classifier: Programming Language :: Python :: 2.6
Classifier: Programming Language :: Python :: 2.7
Classifier: Topic :: Internet :: WWW/HTTP
Classifier: Topic :: Security
Classifier: Topic :: System :: Installation/Setup
Classifier: Topic :: System :: Networking
Classifier: Topic :: System :: Systems Administration
Classifier: Topic :: Utilities
Requires-Dist: certbot-apache
Requires-Dist: letsencrypt (==0.7.0)
